ragoon/__init__.py
ragoon/_decorators.py
ragoon/_logger.py
ragoon/_retrieval.py
ragoon/_scrape.py
ragoon/_search.py
ragoon/chunks.py
ragoon/datasets.py
ragoon/embeddings.py
ragoon/similarity_search.py
ragoon/web_rag.py
ragoon-0.0.15.dist-info/LICENSE
ragoon-0.0.15.dist-info/METADATA
ragoon-0.0.15.dist-info/WHEEL
ragoon-0.0.15.dist-info/top_level.txt
ragoon-0.0.15.dist-info/RECORD
