Metadata-Version: 2.1
Name: ragoon
Version: 0.0.15
Summary: RAGoon : High level library for batched embeddings generation, blazingly-fast web-based RAG and quantized indexes processing ⚡
Keywords: language-models,retrieval,web-scraping,few-shot-learning,nlp,machine-learning,retrieval-augmented-generation,RAG,groq,generative-ai,llama,Mistral,embeddings,BERT,plot,RAGoon
Classifier: Programming Language :: Python
Classifier: Programming Language :: Python :: 3
Classifier: Intended Audience :: Developers
Classifier: Intended Audience :: Science/Research
Classifier: Topic :: Scientific/Engineering :: Artificial Intelligence
Classifier: Topic :: Software Development
Classifier: Topic :: Software Development :: Libraries
Classifier: Topic :: Software Development :: Libraries :: Python Modules
Requires-Python: >=3.9
License-File: LICENSE
Requires-Dist: beautifulsoup4>=4.12.3
Requires-Dist: datasets>=2.20.0
Requires-Dist: faiss-cpu>=1.8.0
Requires-Dist: google-api-python-client>=2.126.0
Requires-Dist: groq>=0.9.0
Requires-Dist: httpx>=0.27.0
Requires-Dist: huggingface-hub>=0.24.2
Requires-Dist: myst-parser>=3.0.1
Requires-Dist: numpy<2
Requires-Dist: numpydoc>=1.7.0
Requires-Dist: openai>=1.37.1
Requires-Dist: overload>=1.1
Requires-Dist: plotly>=5.23.0
Requires-Dist: pydata-sphinx-theme>=0.15.4
Requires-Dist: pytest>=8.3.2
Requires-Dist: scikit-learn>=1.5.1
Requires-Dist: sentence-transformers>=3.1.1
Requires-Dist: sphinx>=7.4.7
Requires-Dist: sphinx-book-theme>=1.1.3
Requires-Dist: torch>=2.3.1
Requires-Dist: transformers
Requires-Dist: tqdm>=4.66.4
Requires-Dist: umap>=0.1.1
Requires-Dist: umap-learn>=0.5.6
Requires-Dist: usearch>=2.12.0
Provides-Extra: docs
Requires-Dist: sphinx>=6.0.0; extra == "docs"
Requires-Dist: sphinx-book-theme>=1.0.1; extra == "docs"
Requires-Dist: sphinxcontrib-katex; extra == "docs"
Requires-Dist: sphinx-autodoc-typehints; extra == "docs"
Requires-Dist: ipython>=8.8.0; extra == "docs"
Requires-Dist: myst-nb>=1.0.0; extra == "docs"
Requires-Dist: myst-parser; extra == "docs"
Requires-Dist: matplotlib>=3.5.0; extra == "docs"
Requires-Dist: sphinx-book-theme==1.1.3; extra == "docs"
Requires-Dist: sphinx-gallery>=0.14.0; extra == "docs"
Requires-Dist: sphinx-collections>=0.0.1; extra == "docs"
Requires-Dist: tensorflow>=2.4.0; extra == "docs"
Requires-Dist: tensorflow-datasets>=4.2.0; extra == "docs"
Requires-Dist: flax; extra == "docs"
Requires-Dist: sphinx-contributors; extra == "docs"
